snake2/__init__.py
snake2/__main__.py
snake2/snake_main.py
icenter_snake2-0.1.0.dist-info/LICENSE
icenter_snake2-0.1.0.dist-info/METADATA
icenter_snake2-0.1.0.dist-info/WHEEL
icenter_snake2-0.1.0.dist-info/top_level.txt
icenter_snake2-0.1.0.dist-info/RECORD
