Metadata-Version: 2.1
Name: icenter-snake2
Version: 0.1.0
Summary: Pygame implementation of the snake video game
Home-page: https://pypi.org/project/icenter_snake2
Author: James Kabbes
Author-email: james.kabbes@gmail.com
Project-URL: GitHub, https://github.com/AmerenICenter/snake2
Project-URL: Documentation, https://amerenicenter.github.io/snake2/
Classifier: Programming Language :: Python :: 3
Classifier: License :: OSI Approved :: MIT License
Classifier: Operating System :: OS Independent
Requires-Python: >=3.7
License-File: LICENSE
